ccdproc/__init__.py
ccdproc/_version.py
ccdproc/ccddata.py
ccdproc/combiner.py
ccdproc/conftest.py
ccdproc/core.py
ccdproc/image_collection.py
ccdproc/log_meta.py
ccdproc/tests/__init__.py
ccdproc/tests/make_mef.py
ccdproc/tests/pytest_fixtures.py
ccdproc/tests/run_for_memory_profile.py
ccdproc/tests/run_profile.ipynb
ccdproc/tests/run_with_file_number_limit.py
ccdproc/tests/test_bitfield.py
ccdproc/tests/test_ccdmask.py
ccdproc/tests/test_ccdproc.py
ccdproc/tests/test_ccdproc_logging.py
ccdproc/tests/test_combine_open_files.py
ccdproc/tests/test_combiner.py
ccdproc/tests/test_cosmicray.py
ccdproc/tests/test_gain.py
ccdproc/tests/test_image_collection.py
ccdproc/tests/test_keyword.py
ccdproc/tests/test_memory_use.py
ccdproc/tests/test_rebin.py
ccdproc/tests/test_wrapped_external_funcs.py
ccdproc/tests/data/README.rst
ccdproc/tests/data/a8280271.fits
ccdproc/tests/data/expected_ifc_file_properties.csv
ccdproc/tests/data/flat-mef.fits
ccdproc/tests/data/science-mef.fits
ccdproc/tests/data/sip-wcs.fit
ccdproc/utils/__init__.py
ccdproc/utils/sample_directory.py
ccdproc/utils/slices.py
ccdproc/utils/tests/__init__.py
ccdproc/utils/tests/test_slices.py
ccdproc-2.5.0.dist-info/METADATA
ccdproc-2.5.0.dist-info/WHEEL
ccdproc-2.5.0.dist-info/licenses/AUTHORS.rst
ccdproc-2.5.0.dist-info/licenses/LICENSE.rst
ccdproc-2.5.0.dist-info/RECORD
