Metadata-Version: 2.4
Name: ccdproc
Version: 2.5.0
Summary: Astropy affiliated package
Project-URL: Homepage, https://ccdproc.readthedocs.io/
Author: Matt Craig, and Michael Seifert
Author-email: Steve Crawford <ccdproc@gmail.com>
License: BSD-3-Clause
License-File: AUTHORS.rst
License-File: LICENSE.rst
Requires-Python: >=3.8
Requires-Dist: astropy>=5.0.1
Requires-Dist: astroscrappy>=1.1.0
Requires-Dist: numpy>=1.24
Requires-Dist: reproject>=0.7
Requires-Dist: scikit-image
Requires-Dist: scipy
Provides-Extra: docs
Requires-Dist: matplotlib; extra == 'docs'
Requires-Dist: sphinx-astropy; extra == 'docs'
Provides-Extra: test
Requires-Dist: black; extra == 'test'
Requires-Dist: memory-profiler; extra == 'test'
Requires-Dist: pre-commit; extra == 'test'
Requires-Dist: pytest-astropy>=0.10.0; extra == 'test'
Requires-Dist: ruff; extra == 'test'
